alphabuilder_optimizer/__init__.py
alphabuilder_optimizer/app.py
alphabuilder_optimizer-0.0.1.3.dist-info/METADATA
alphabuilder_optimizer-0.0.1.3.dist-info/WHEEL
alphabuilder_optimizer-0.0.1.3.dist-info/top_level.txt
alphabuilder_optimizer-0.0.1.3.dist-info/RECORD
